{
  "current_action": "idle",
  "events": [
    {
      "level": "info",
      "message": "Run started (interval)",
      "ts": "2026-03-11T00:28:59.023607+00:00"
    },
    {
      "level": "info",
      "message": "Run finished successfully",
      "ts": "2026-03-11T00:29:12.880229+00:00"
    },
    {
      "level": "info",
      "message": "Run started (interval)",
      "ts": "2026-03-11T00:32:51.790811+00:00"
    },
    {
      "level": "info",
      "message": "Run finished successfully",
      "ts": "2026-03-11T00:33:02.801622+00:00"
    },
    {
      "level": "info",
      "message": "Run started (interval)",
      "ts": "2026-03-11T00:34:30.673492+00:00"
    },
    {
      "level": "info",
      "message": "Run finished successfully",
      "ts": "2026-03-11T00:34:42.472488+00:00"
    },
    {
      "level": "info",
      "message": "Run started (interval)",
      "ts": "2026-03-11T03:35:47.882496+00:00"
    },
    {
      "level": "info",
      "message": "Run finished successfully",
      "ts": "2026-03-11T03:36:01.865369+00:00"
    },
    {
      "level": "info",
      "message": "Run started (interval)",
      "ts": "2026-03-11T03:39:09.772066+00:00"
    },
    {
      "level": "info",
      "message": "Run finished successfully",
      "ts": "2026-03-11T03:39:21.349196+00:00"
    },
    {
      "level": "info",
      "message": "Run started (interval)",
      "ts": "2026-03-11T03:41:10.152376+00:00"
    },
    {
      "level": "info",
      "message": "Run finished successfully",
      "ts": "2026-03-11T03:41:21.609338+00:00"
    },
    {
      "level": "info",
      "message": "Run started (interval)",
      "ts": "2026-03-11T03:43:10.182432+00:00"
    },
    {
      "level": "info",
      "message": "Run finished successfully",
      "ts": "2026-03-11T03:43:22.687620+00:00"
    },
    {
      "level": "info",
      "message": "Run started (interval)",
      "ts": "2026-03-11T03:45:09.715495+00:00"
    },
    {
      "level": "info",
      "message": "Run finished successfully",
      "ts": "2026-03-11T03:45:22.252926+00:00"
    },
    {
      "level": "info",
      "message": "Run started (interval)",
      "ts": "2026-03-11T03:47:09.688596+00:00"
    },
    {
      "level": "info",
      "message": "Run finished successfully",
      "ts": "2026-03-11T03:47:22.427531+00:00"
    },
    {
      "level": "info",
      "message": "Run started (interval)",
      "ts": "2026-03-11T03:49:09.769476+00:00"
    },
    {
      "level": "info",
      "message": "Run finished successfully",
      "ts": "2026-03-11T03:49:23.906353+00:00"
    },
    {
      "level": "info",
      "message": "Run started (interval)",
      "ts": "2026-03-11T03:51:09.713811+00:00"
    },
    {
      "level": "info",
      "message": "Run finished successfully",
      "ts": "2026-03-11T03:51:23.804787+00:00"
    },
    {
      "level": "info",
      "message": "Run started (interval)",
      "ts": "2026-03-11T03:53:09.673486+00:00"
    },
    {
      "level": "info",
      "message": "Run finished successfully",
      "ts": "2026-03-11T03:53:23.514140+00:00"
    },
    {
      "level": "info",
      "message": "Run started (interval)",
      "ts": "2026-03-11T03:55:09.696316+00:00"
    },
    {
      "level": "info",
      "message": "Run finished successfully",
      "ts": "2026-03-11T03:55:21.652782+00:00"
    },
    {
      "level": "info",
      "message": "Run started (interval)",
      "ts": "2026-03-11T03:57:09.880138+00:00"
    },
    {
      "level": "info",
      "message": "Run finished successfully",
      "ts": "2026-03-11T03:57:23.190622+00:00"
    },
    {
      "level": "info",
      "message": "Run started (interval)",
      "ts": "2026-03-11T03:59:09.686015+00:00"
    },
    {
      "level": "info",
      "message": "Run finished successfully",
      "ts": "2026-03-11T03:59:22.292341+00:00"
    },
    {
      "level": "info",
      "message": "Run started (interval)",
      "ts": "2026-03-11T04:01:09.706024+00:00"
    },
    {
      "level": "info",
      "message": "Run finished successfully",
      "ts": "2026-03-11T04:01:22.245511+00:00"
    },
    {
      "level": "info",
      "message": "Run started (interval)",
      "ts": "2026-03-11T04:03:09.801918+00:00"
    },
    {
      "level": "info",
      "message": "Run finished successfully",
      "ts": "2026-03-11T04:03:21.704133+00:00"
    },
    {
      "level": "info",
      "message": "Run started (interval)",
      "ts": "2026-03-11T04:05:07.636067+00:00"
    },
    {
      "level": "info",
      "message": "Run finished successfully",
      "ts": "2026-03-11T04:05:19.488307+00:00"
    },
    {
      "level": "info",
      "message": "Run started (interval)",
      "ts": "2026-03-11T04:07:09.734183+00:00"
    },
    {
      "level": "info",
      "message": "Run finished successfully",
      "ts": "2026-03-11T04:07:21.808156+00:00"
    },
    {
      "level": "info",
      "message": "Run started (interval)",
      "ts": "2026-03-11T04:09:09.689994+00:00"
    },
    {
      "level": "info",
      "message": "Run finished successfully",
      "ts": "2026-03-11T04:09:22.959541+00:00"
    },
    {
      "level": "info",
      "message": "Run started (interval)",
      "ts": "2026-03-11T04:11:09.679558+00:00"
    },
    {
      "level": "info",
      "message": "Run finished successfully",
      "ts": "2026-03-11T04:11:20.548067+00:00"
    },
    {
      "level": "info",
      "message": "Run started (interval)",
      "ts": "2026-03-11T04:13:09.702115+00:00"
    },
    {
      "level": "info",
      "message": "Run finished successfully",
      "ts": "2026-03-11T04:13:21.348808+00:00"
    },
    {
      "level": "info",
      "message": "Run started (interval)",
      "ts": "2026-03-11T04:15:09.685024+00:00"
    },
    {
      "level": "info",
      "message": "Run finished successfully",
      "ts": "2026-03-11T04:15:23.612165+00:00"
    },
    {
      "level": "info",
      "message": "Run started (interval)",
      "ts": "2026-03-11T04:17:09.918289+00:00"
    },
    {
      "level": "info",
      "message": "Run finished successfully",
      "ts": "2026-03-11T04:17:20.916357+00:00"
    },
    {
      "level": "info",
      "message": "Run started (interval)",
      "ts": "2026-03-11T04:19:09.687589+00:00"
    },
    {
      "level": "info",
      "message": "Run finished successfully",
      "ts": "2026-03-11T04:19:22.025996+00:00"
    },
    {
      "level": "info",
      "message": "Run started (interval)",
      "ts": "2026-03-11T04:21:09.704925+00:00"
    },
    {
      "level": "info",
      "message": "Run finished successfully",
      "ts": "2026-03-11T04:21:22.214525+00:00"
    },
    {
      "level": "info",
      "message": "Run started (interval)",
      "ts": "2026-03-11T04:23:09.683277+00:00"
    },
    {
      "level": "info",
      "message": "Run finished successfully",
      "ts": "2026-03-11T04:23:22.377763+00:00"
    },
    {
      "level": "info",
      "message": "Run started (interval)",
      "ts": "2026-03-11T04:25:09.745077+00:00"
    },
    {
      "level": "info",
      "message": "Run finished successfully",
      "ts": "2026-03-11T04:25:21.804242+00:00"
    },
    {
      "level": "info",
      "message": "Run started (interval)",
      "ts": "2026-03-11T04:27:09.699008+00:00"
    },
    {
      "level": "info",
      "message": "Run finished successfully",
      "ts": "2026-03-11T04:27:22.942831+00:00"
    },
    {
      "level": "info",
      "message": "Run started (interval)",
      "ts": "2026-03-11T04:29:09.689521+00:00"
    },
    {
      "level": "info",
      "message": "Run finished successfully",
      "ts": "2026-03-11T04:29:22.627011+00:00"
    },
    {
      "level": "info",
      "message": "Run started (interval)",
      "ts": "2026-03-11T04:31:09.687392+00:00"
    },
    {
      "level": "info",
      "message": "Run finished successfully",
      "ts": "2026-03-11T04:31:21.757164+00:00"
    },
    {
      "level": "info",
      "message": "Run started (interval)",
      "ts": "2026-03-11T04:33:09.706334+00:00"
    },
    {
      "level": "info",
      "message": "Run finished successfully",
      "ts": "2026-03-11T04:33:20.848272+00:00"
    },
    {
      "level": "info",
      "message": "Run started (interval)",
      "ts": "2026-03-11T04:35:07.755655+00:00"
    },
    {
      "level": "info",
      "message": "Run finished successfully",
      "ts": "2026-03-11T04:35:20.563463+00:00"
    },
    {
      "level": "info",
      "message": "Run started (interval)",
      "ts": "2026-03-11T04:37:09.682391+00:00"
    },
    {
      "level": "info",
      "message": "Run finished successfully",
      "ts": "2026-03-11T04:37:22.643869+00:00"
    },
    {
      "level": "info",
      "message": "Run started (interval)",
      "ts": "2026-03-11T04:39:09.686226+00:00"
    },
    {
      "level": "info",
      "message": "Run finished successfully",
      "ts": "2026-03-11T04:39:21.761845+00:00"
    },
    {
      "level": "info",
      "message": "Run started (interval)",
      "ts": "2026-03-11T04:41:09.672801+00:00"
    },
    {
      "level": "info",
      "message": "Run finished successfully",
      "ts": "2026-03-11T04:41:23.246115+00:00"
    },
    {
      "level": "info",
      "message": "Run started (interval)",
      "ts": "2026-03-11T04:43:09.692630+00:00"
    },
    {
      "level": "info",
      "message": "Run finished successfully",
      "ts": "2026-03-11T04:43:21.210916+00:00"
    },
    {
      "level": "info",
      "message": "Run started (interval)",
      "ts": "2026-03-11T04:45:09.687956+00:00"
    },
    {
      "level": "info",
      "message": "Run finished successfully",
      "ts": "2026-03-11T04:45:22.654624+00:00"
    },
    {
      "level": "info",
      "message": "Run started (interval)",
      "ts": "2026-03-11T04:47:09.666439+00:00"
    },
    {
      "level": "info",
      "message": "Run finished successfully",
      "ts": "2026-03-11T04:47:23.025523+00:00"
    },
    {
      "level": "info",
      "message": "Run started (interval)",
      "ts": "2026-03-11T04:49:09.702893+00:00"
    },
    {
      "level": "info",
      "message": "Run finished successfully",
      "ts": "2026-03-11T04:49:21.460358+00:00"
    },
    {
      "level": "info",
      "message": "Run started (interval)",
      "ts": "2026-03-11T04:51:09.707322+00:00"
    },
    {
      "level": "info",
      "message": "Run finished successfully",
      "ts": "2026-03-11T04:51:23.300968+00:00"
    },
    {
      "level": "info",
      "message": "Run started (interval)",
      "ts": "2026-03-11T04:53:09.679999+00:00"
    },
    {
      "level": "info",
      "message": "Run finished successfully",
      "ts": "2026-03-11T04:53:22.013906+00:00"
    },
    {
      "level": "info",
      "message": "Run started (interval)",
      "ts": "2026-03-11T04:55:09.679281+00:00"
    },
    {
      "level": "info",
      "message": "Run finished successfully",
      "ts": "2026-03-11T04:55:21.281651+00:00"
    },
    {
      "level": "info",
      "message": "Run started (interval)",
      "ts": "2026-03-11T04:57:09.928554+00:00"
    },
    {
      "level": "info",
      "message": "Run finished successfully",
      "ts": "2026-03-11T04:57:22.342466+00:00"
    },
    {
      "level": "info",
      "message": "Run started (interval)",
      "ts": "2026-03-11T04:59:09.847494+00:00"
    },
    {
      "level": "info",
      "message": "Run finished successfully",
      "ts": "2026-03-11T04:59:23.975406+00:00"
    },
    {
      "level": "info",
      "message": "Run started (interval)",
      "ts": "2026-03-11T05:01:09.717073+00:00"
    },
    {
      "level": "info",
      "message": "Run finished successfully",
      "ts": "2026-03-11T05:01:21.969941+00:00"
    },
    {
      "level": "info",
      "message": "Run started (interval)",
      "ts": "2026-03-11T05:03:09.876319+00:00"
    },
    {
      "level": "info",
      "message": "Run finished successfully",
      "ts": "2026-03-11T05:03:20.899020+00:00"
    },
    {
      "level": "info",
      "message": "Run started (interval)",
      "ts": "2026-03-11T05:05:32.637441+00:00"
    },
    {
      "level": "info",
      "message": "Run finished successfully",
      "ts": "2026-03-11T05:05:46.118586+00:00"
    },
    {
      "level": "info",
      "message": "Run started (interval)",
      "ts": "2026-03-11T05:07:09.671879+00:00"
    },
    {
      "level": "info",
      "message": "Run finished successfully",
      "ts": "2026-03-11T05:07:22.593188+00:00"
    },
    {
      "level": "info",
      "message": "Run started (interval)",
      "ts": "2026-03-11T05:09:09.732052+00:00"
    },
    {
      "level": "info",
      "message": "Run finished successfully",
      "ts": "2026-03-11T05:09:21.004076+00:00"
    },
    {
      "level": "info",
      "message": "Run started (interval)",
      "ts": "2026-03-11T05:11:09.670353+00:00"
    },
    {
      "level": "info",
      "message": "Run finished successfully",
      "ts": "2026-03-11T05:11:22.829190+00:00"
    },
    {
      "level": "info",
      "message": "Run started (interval)",
      "ts": "2026-03-11T05:13:09.943636+00:00"
    },
    {
      "level": "info",
      "message": "Run finished successfully",
      "ts": "2026-03-11T05:13:23.614194+00:00"
    },
    {
      "level": "info",
      "message": "Run started (interval)",
      "ts": "2026-03-11T05:15:09.743269+00:00"
    },
    {
      "level": "info",
      "message": "Run finished successfully",
      "ts": "2026-03-11T05:15:22.964853+00:00"
    },
    {
      "level": "info",
      "message": "Run started (interval)",
      "ts": "2026-03-11T05:17:09.663529+00:00"
    },
    {
      "level": "info",
      "message": "Run finished successfully",
      "ts": "2026-03-11T05:17:22.118941+00:00"
    },
    {
      "level": "info",
      "message": "Run started (interval)",
      "ts": "2026-03-11T05:19:09.994721+00:00"
    },
    {
      "level": "info",
      "message": "Run finished successfully",
      "ts": "2026-03-11T05:19:20.832577+00:00"
    },
    {
      "level": "info",
      "message": "Run started (interval)",
      "ts": "2026-03-11T05:21:09.899896+00:00"
    },
    {
      "level": "info",
      "message": "Run finished successfully",
      "ts": "2026-03-11T05:21:22.526936+00:00"
    },
    {
      "level": "info",
      "message": "Run started (interval)",
      "ts": "2026-03-11T05:23:09.655319+00:00"
    },
    {
      "level": "info",
      "message": "Run finished successfully",
      "ts": "2026-03-11T05:23:22.899833+00:00"
    },
    {
      "level": "info",
      "message": "Run started (interval)",
      "ts": "2026-03-11T05:25:09.941842+00:00"
    },
    {
      "level": "info",
      "message": "Run finished successfully",
      "ts": "2026-03-11T05:25:22.574812+00:00"
    },
    {
      "level": "info",
      "message": "Run started (interval)",
      "ts": "2026-03-11T05:27:09.659456+00:00"
    },
    {
      "level": "info",
      "message": "Run finished successfully",
      "ts": "2026-03-11T05:27:21.517655+00:00"
    },
    {
      "level": "info",
      "message": "Run started (interval)",
      "ts": "2026-03-11T05:29:09.684716+00:00"
    },
    {
      "level": "info",
      "message": "Run finished successfully",
      "ts": "2026-03-11T05:29:22.528788+00:00"
    },
    {
      "level": "info",
      "message": "Run started (interval)",
      "ts": "2026-03-11T05:31:09.635268+00:00"
    },
    {
      "level": "info",
      "message": "Run finished successfully",
      "ts": "2026-03-11T05:31:22.408641+00:00"
    },
    {
      "level": "info",
      "message": "Run started (interval)",
      "ts": "2026-03-11T05:33:10.033464+00:00"
    },
    {
      "level": "info",
      "message": "Run finished successfully",
      "ts": "2026-03-11T05:33:21.630174+00:00"
    },
    {
      "level": "info",
      "message": "Run started (interval)",
      "ts": "2026-03-11T05:35:38.633390+00:00"
    },
    {
      "level": "info",
      "message": "Run finished successfully",
      "ts": "2026-03-11T05:35:49.525971+00:00"
    },
    {
      "level": "info",
      "message": "Run started (interval)",
      "ts": "2026-03-11T05:37:09.664108+00:00"
    },
    {
      "level": "info",
      "message": "Run finished successfully",
      "ts": "2026-03-11T05:37:23.271465+00:00"
    },
    {
      "level": "info",
      "message": "Run started (interval)",
      "ts": "2026-03-11T05:39:09.886953+00:00"
    },
    {
      "level": "info",
      "message": "Run finished successfully",
      "ts": "2026-03-11T05:39:22.260266+00:00"
    },
    {
      "level": "info",
      "message": "Run started (interval)",
      "ts": "2026-03-11T05:41:09.661506+00:00"
    },
    {
      "level": "info",
      "message": "Run finished successfully",
      "ts": "2026-03-11T05:41:21.953132+00:00"
    },
    {
      "level": "info",
      "message": "Run started (interval)",
      "ts": "2026-03-11T05:43:09.647206+00:00"
    },
    {
      "level": "info",
      "message": "Run finished successfully",
      "ts": "2026-03-11T05:43:21.264733+00:00"
    },
    {
      "level": "info",
      "message": "Run started (interval)",
      "ts": "2026-03-11T05:45:09.900262+00:00"
    },
    {
      "level": "info",
      "message": "Run finished successfully",
      "ts": "2026-03-11T05:45:22.546138+00:00"
    },
    {
      "level": "info",
      "message": "Run started (interval)",
      "ts": "2026-03-11T05:47:09.677177+00:00"
    },
    {
      "level": "info",
      "message": "Run finished successfully",
      "ts": "2026-03-11T05:47:20.888531+00:00"
    },
    {
      "level": "info",
      "message": "Run started (interval)",
      "ts": "2026-03-11T05:49:09.659364+00:00"
    },
    {
      "level": "info",
      "message": "Run finished successfully",
      "ts": "2026-03-11T05:49:21.168664+00:00"
    },
    {
      "level": "info",
      "message": "Run started (interval)",
      "ts": "2026-03-11T05:51:09.668002+00:00"
    },
    {
      "level": "info",
      "message": "Run finished successfully",
      "ts": "2026-03-11T05:51:21.317034+00:00"
    },
    {
      "level": "info",
      "message": "Run started (interval)",
      "ts": "2026-03-11T05:53:09.751551+00:00"
    },
    {
      "level": "info",
      "message": "Run finished successfully",
      "ts": "2026-03-11T05:53:21.565843+00:00"
    },
    {
      "level": "info",
      "message": "Run started (interval)",
      "ts": "2026-03-11T05:55:09.825585+00:00"
    },
    {
      "level": "info",
      "message": "Run finished successfully",
      "ts": "2026-03-11T05:55:20.326591+00:00"
    },
    {
      "level": "info",
      "message": "Run started (interval)",
      "ts": "2026-03-11T05:57:10.172932+00:00"
    },
    {
      "level": "info",
      "message": "Run finished successfully",
      "ts": "2026-03-11T05:57:21.092397+00:00"
    },
    {
      "level": "info",
      "message": "Run started (interval)",
      "ts": "2026-03-11T05:59:09.674293+00:00"
    },
    {
      "level": "info",
      "message": "Run finished successfully",
      "ts": "2026-03-11T05:59:22.082162+00:00"
    },
    {
      "level": "info",
      "message": "Run started (interval)",
      "ts": "2026-03-11T06:01:09.668503+00:00"
    },
    {
      "level": "info",
      "message": "Run finished successfully",
      "ts": "2026-03-11T06:01:22.251816+00:00"
    },
    {
      "level": "info",
      "message": "Run started (interval)",
      "ts": "2026-03-11T06:03:09.718726+00:00"
    },
    {
      "level": "info",
      "message": "Run finished successfully",
      "ts": "2026-03-11T06:03:21.488727+00:00"
    },
    {
      "level": "info",
      "message": "Run started (interval)",
      "ts": "2026-03-11T06:05:41.861528+00:00"
    },
    {
      "level": "info",
      "message": "Run finished successfully",
      "ts": "2026-03-11T06:05:53.526193+00:00"
    },
    {
      "level": "info",
      "message": "Run started (interval)",
      "ts": "2026-03-11T06:07:11.852706+00:00"
    },
    {
      "level": "info",
      "message": "Run finished successfully",
      "ts": "2026-03-11T06:07:23.857531+00:00"
    },
    {
      "level": "info",
      "message": "Run started (interval)",
      "ts": "2026-03-11T06:09:11.769371+00:00"
    },
    {
      "level": "info",
      "message": "Run finished successfully",
      "ts": "2026-03-11T06:09:22.292869+00:00"
    },
    {
      "level": "info",
      "message": "Run started (interval)",
      "ts": "2026-03-11T06:11:11.730753+00:00"
    },
    {
      "level": "info",
      "message": "Run finished successfully",
      "ts": "2026-03-11T06:11:25.190261+00:00"
    },
    {
      "level": "info",
      "message": "Run started (interval)",
      "ts": "2026-03-11T06:13:11.733049+00:00"
    },
    {
      "level": "info",
      "message": "Run finished successfully",
      "ts": "2026-03-11T06:13:23.835975+00:00"
    },
    {
      "level": "info",
      "message": "Run started (interval)",
      "ts": "2026-03-11T06:15:11.939405+00:00"
    },
    {
      "level": "info",
      "message": "Run finished successfully",
      "ts": "2026-03-11T06:15:25.157321+00:00"
    },
    {
      "level": "info",
      "message": "Run started (interval)",
      "ts": "2026-03-11T06:17:11.634369+00:00"
    },
    {
      "level": "info",
      "message": "Run finished successfully",
      "ts": "2026-03-11T06:17:24.849130+00:00"
    },
    {
      "level": "info",
      "message": "Run started (interval)",
      "ts": "2026-03-11T06:19:11.646746+00:00"
    },
    {
      "level": "info",
      "message": "Run finished successfully",
      "ts": "2026-03-11T06:19:24.783836+00:00"
    },
    {
      "level": "info",
      "message": "Run started (interval)",
      "ts": "2026-03-11T06:21:11.621876+00:00"
    },
    {
      "level": "info",
      "message": "Run finished successfully",
      "ts": "2026-03-11T06:21:25.747489+00:00"
    },
    {
      "level": "info",
      "message": "Run started (interval)",
      "ts": "2026-03-11T06:23:11.601920+00:00"
    },
    {
      "level": "info",
      "message": "Run finished successfully",
      "ts": "2026-03-11T06:23:25.115093+00:00"
    },
    {
      "level": "info",
      "message": "Run started (interval)",
      "ts": "2026-03-11T06:25:12.183589+00:00"
    },
    {
      "level": "info",
      "message": "Run finished successfully",
      "ts": "2026-03-11T06:25:23.479838+00:00"
    },
    {
      "level": "info",
      "message": "Run started (interval)",
      "ts": "2026-03-11T06:27:11.640404+00:00"
    },
    {
      "level": "info",
      "message": "Run finished successfully",
      "ts": "2026-03-11T06:27:25.025284+00:00"
    },
    {
      "level": "info",
      "message": "Run started (interval)",
      "ts": "2026-03-11T06:29:11.642608+00:00"
    },
    {
      "level": "info",
      "message": "Run finished successfully",
      "ts": "2026-03-11T06:29:24.170303+00:00"
    },
    {
      "level": "info",
      "message": "Run started (interval)",
      "ts": "2026-03-11T06:31:12.005251+00:00"
    },
    {
      "level": "info",
      "message": "Run finished successfully",
      "ts": "2026-03-11T06:31:24.501584+00:00"
    },
    {
      "level": "info",
      "message": "Run started (interval)",
      "ts": "2026-03-11T06:33:11.616132+00:00"
    },
    {
      "level": "info",
      "message": "Run finished successfully",
      "ts": "2026-03-11T06:33:25.416946+00:00"
    },
    {
      "level": "info",
      "message": "Run started (interval)",
      "ts": "2026-03-11T06:35:43.782125+00:00"
    },
    {
      "level": "info",
      "message": "Run finished successfully",
      "ts": "2026-03-11T06:35:55.424337+00:00"
    },
    {
      "level": "info",
      "message": "Run started (interval)",
      "ts": "2026-03-11T06:37:13.833409+00:00"
    },
    {
      "level": "info",
      "message": "Run finished successfully",
      "ts": "2026-03-11T06:37:24.814658+00:00"
    },
    {
      "level": "info",
      "message": "Run started (interval)",
      "ts": "2026-03-11T06:39:13.631915+00:00"
    },
    {
      "level": "info",
      "message": "Run finished successfully",
      "ts": "2026-03-11T06:39:26.323926+00:00"
    },
    {
      "level": "info",
      "message": "Run started (interval)",
      "ts": "2026-03-11T06:41:13.592591+00:00"
    },
    {
      "level": "info",
      "message": "Run finished successfully",
      "ts": "2026-03-11T06:41:26.019569+00:00"
    },
    {
      "level": "info",
      "message": "Run started (interval)",
      "ts": "2026-03-11T06:43:13.616501+00:00"
    },
    {
      "level": "info",
      "message": "Run finished successfully",
      "ts": "2026-03-11T06:43:25.707351+00:00"
    },
    {
      "level": "info",
      "message": "Run started (interval)",
      "ts": "2026-03-11T06:45:13.594575+00:00"
    },
    {
      "level": "info",
      "message": "Run finished successfully",
      "ts": "2026-03-11T06:45:25.959740+00:00"
    },
    {
      "level": "info",
      "message": "Run started (interval)",
      "ts": "2026-03-11T06:47:13.605287+00:00"
    },
    {
      "level": "info",
      "message": "Run finished successfully",
      "ts": "2026-03-11T06:47:27.317864+00:00"
    },
    {
      "level": "info",
      "message": "Run started (interval)",
      "ts": "2026-03-11T06:49:13.640985+00:00"
    },
    {
      "level": "info",
      "message": "Run finished successfully",
      "ts": "2026-03-11T06:49:25.740461+00:00"
    }
  ],
  "last_run_finished_at": "2026-03-11T06:49:25.740013+00:00",
  "last_run_result": "ok",
  "last_run_started_at": "2026-03-11T06:49:13.640972+00:00",
  "last_run_summary": {
    "checked_threads": 4,
    "errors": [],
    "finished_at": "2026-03-11T06:49:25.740013+00:00",
    "reason": "interval",
    "requests_made": 5,
    "started_at": "2026-03-11T06:49:14.580019+00:00",
    "updated_threads": 4
  },
  "next_run_at": "2026-03-11T06:50:25.740446+00:00"
}
